{
    "fluentMethods": true,
    "relationships": [
        {
            "relationshipType": "many-to-one",
            "relationshipName": "user",
            "otherEntityName": "user",
            "otherEntityField": "login"
        },
        {
            "relationshipType": "many-to-one",
            "relationshipName": "photo",
            "otherEntityName": "user",
            "otherEntityField": "login"
        },
        {
            "relationshipType": "many-to-one",
            "relationshipName": "offer",
            "otherEntityName": "user",
            "otherEntityField": "login"
        }
    ],
    "fields": [
        {
            "fieldName": "message",
            "fieldType": "String"
        },
        {
            "fieldName": "title",
            "fieldType": "String"
        }
    ],
    "changelogDate": "20170210163001",
    "dto": "no",
    "service": "no",
    "entityTableName": "report",
    "pagination": "no"
}
